binprint/__init__.py
binprint/binprint.py
binprint-0.1.dist-info/LICENSE
binprint-0.1.dist-info/METADATA
binprint-0.1.dist-info/WHEEL
binprint-0.1.dist-info/top_level.txt
binprint-0.1.dist-info/RECORD
