Metadata-Version: 2.1
Name: binprint
Version: 0.1
Summary: Simple package to pretty print binary data in python
Home-page: https://github.com/mirusu400/binprint
Author: Seong Jin Kim
Author-email: mirusu400@naver.com
License: UNKNOWN
Keywords: binary,Pretty print,Python,Hex dump,Ascii dump,hex,dump
Platform: UNKNOWN
Classifier: Programming Language :: Python :: 3
Classifier: Programming Language :: Python :: 3.2
Classifier: Programming Language :: Python :: 3.3
Classifier: Programming Language :: Python :: 3.4
Classifier: Programming Language :: Python :: 3.5
Classifier: Programming Language :: Python :: 3.6
Classifier: Programming Language :: Python :: 3.7
Classifier: Programming Language :: Python :: 3.8
Classifier: Programming Language :: Python :: 3.9
Classifier: Programming Language :: Python :: 3.10
Requires-Python: >=3
License-File: LICENSE
